pillar1/__init__.py
pillar1/constants.py
pillar1/constants_original.py
pillar1/pillar1.py
pillar1-0.1.9.40.dist-info/METADATA
pillar1-0.1.9.40.dist-info/WHEEL
pillar1-0.1.9.40.dist-info/top_level.txt
pillar1-0.1.9.40.dist-info/RECORD
