Metadata-Version: 2.1
Name: pillar1
Version: 0.1.9.40
Summary: Official package for Pillar1 company
Home-page: https://github.com/amhajja/pillar1
Author: Ayman Hajja
Author-email: amhajja@gmail.com
Classifier: Programming Language :: Python :: 3
Classifier: License :: OSI Approved :: MIT License
Requires-Python: >=3.9
Requires-Dist: ipywidgets
Requires-Dist: google-cloud-aiplatform
Requires-Dist: boto3
Requires-Dist: pyspark
Requires-Dist: protobuf (==4.23.4)
Requires-Dist: openai (==0.27.8)
